LICENSE
README.md
setup.cfg
setup.py
twitcaspy/__init__.py
twitcaspy/api.py
twitcaspy/errors.py
twitcaspy/utils.py
twitcaspy.egg-info/PKG-INFO
twitcaspy.egg-info/SOURCES.txt
twitcaspy.egg-info/dependency_links.txt
twitcaspy.egg-info/requires.txt
twitcaspy.egg-info/top_level.txt
twitcaspy.egg-info/zip-safe
twitcaspy/auth/__init__.py
twitcaspy/auth/app.py
twitcaspy/auth/auth.py
twitcaspy/auth/grant.py
twitcaspy/auth/implicit.py
twitcaspy/auth/oauth/__init__.py
twitcaspy/auth/oauth/basic.py
twitcaspy/auth/oauth/bearer.py
twitcaspy/models/__init__.py
twitcaspy/models/app.py
twitcaspy/models/category.py
twitcaspy/models/comment.py
twitcaspy/models/factory.py
twitcaspy/models/gift.py
twitcaspy/models/latelimit.py
twitcaspy/models/live.py
twitcaspy/models/model.py
twitcaspy/models/movie.py
twitcaspy/models/raw.py
twitcaspy/models/result.py
twitcaspy/models/subcategory.py
twitcaspy/models/supporter.py
twitcaspy/models/user.py
twitcaspy/models/webhook.py
twitcaspy/parsers/__init__.py
twitcaspy/parsers/jsonparser.py
twitcaspy/parsers/modelparser.py
twitcaspy/parsers/parser.py
twitcaspy/parsers/rawparser.py