Metadata-Version: 2.1
Name: twitcaspy
Version: 1.0.2
Summary: Twitcasting library for Python
Home-page: https://github.com/Alma-field/twitcaspy
Author: Alma field
Author-email: twitcaspy@alma-field.com
License: MIT
Project-URL: Documentation, https://twitcaspy.alma-field.com/
Project-URL: Issue Tracker, https://github.com/Alma-field/twitcaspy/issues
Project-URL: Source Code, https://github.com/Alma-field/twitcaspy
Keywords: twitcasting library
Platform: UNKNOWN
Classifier: Topic :: Software Development :: Libraries
Classifier: License :: OSI Approved :: MIT License
Classifier: Programming Language :: Python
Classifier: Programming Language :: Python :: 3
Classifier: Programming Language :: Python :: 3.7
Classifier: Programming Language :: Python :: 3.8
Classifier: Programming Language :: Python :: 3.9
Classifier: Programming Language :: Python :: 3 :: Only
Requires-Python: >=3.7
Provides-Extra: test
Provides-Extra: example
License-File: LICENSE
